odoo/addons/purchase_minimum_amount/README.rst
odoo/addons/purchase_minimum_amount/__init__.py
odoo/addons/purchase_minimum_amount/__manifest__.py
odoo/addons/purchase_minimum_amount/data/purchase_block_reason_data.xml
odoo/addons/purchase_minimum_amount/i18n/de.po
odoo/addons/purchase_minimum_amount/i18n/es.po
odoo/addons/purchase_minimum_amount/i18n/es_MX.po
odoo/addons/purchase_minimum_amount/i18n/fr.po
odoo/addons/purchase_minimum_amount/i18n/it.po
odoo/addons/purchase_minimum_amount/i18n/pt_BR.po
odoo/addons/purchase_minimum_amount/i18n/purchase_minimum_amount.pot
odoo/addons/purchase_minimum_amount/i18n/sl.po
odoo/addons/purchase_minimum_amount/models/__init__.py
odoo/addons/purchase_minimum_amount/models/partner.py
odoo/addons/purchase_minimum_amount/models/purchase_order.py
odoo/addons/purchase_minimum_amount/readme/CONFIGURE.rst
odoo/addons/purchase_minimum_amount/readme/CONTRIBUTORS.rst
odoo/addons/purchase_minimum_amount/readme/DESCRIPTION.rst
odoo/addons/purchase_minimum_amount/readme/USAGE.rst
odoo/addons/purchase_minimum_amount/static/description/icon.png
odoo/addons/purchase_minimum_amount/static/description/index.html
odoo/addons/purchase_minimum_amount/tests/__init__.py
odoo/addons/purchase_minimum_amount/tests/test_po_minimum_amount_block.py
odoo/addons/purchase_minimum_amount/views/purchase_order_view.xml
odoo/addons/purchase_minimum_amount/views/res_partner_view.xml
odoo13_addon_purchase_minimum_amount-13.0.1.0.1.dist-info/METADATA
odoo13_addon_purchase_minimum_amount-13.0.1.0.1.dist-info/WHEEL
odoo13_addon_purchase_minimum_amount-13.0.1.0.1.dist-info/top_level.txt
odoo13_addon_purchase_minimum_amount-13.0.1.0.1.dist-info/RECORD
